logcrypt/__init__.py
logcrypt/core.py
logcrypt/cryptography.py
logcrypt/cryptography.so
logcrypt/decrypt_log.py
logcrypt/filters.py
logcrypt/formatters.py
logcrypt/key_manager.py
logcrypt/levels.py
logcrypt-1.1.0.dist-info/METADATA
logcrypt-1.1.0.dist-info/WHEEL
logcrypt-1.1.0.dist-info/top_level.txt
logcrypt-1.1.0.dist-info/RECORD
